hintapi/__init__.py
hintapi/__main__.py
hintapi/__version__.py
hintapi/applications.py
hintapi/cli.py
hintapi/debug.py
hintapi/exceptions.py
hintapi/middlewares/__init__.py
hintapi/middlewares/cors.py
hintapi/openapi/__init__.py
hintapi/openapi/application.py
hintapi/openapi/extra_docs.py
hintapi/openapi/schema.py
hintapi/openapi/specification.py
hintapi/openapi/templates/rapidoc.html
hintapi/openapi/templates/redoc.html
hintapi/openapi/templates/swagger.html
hintapi/openapi/types.py
hintapi/parameters/__init__.py
hintapi/parameters/field_functions.py
hintapi/parameters/fields.py
hintapi/py.typed
hintapi/requests.py
hintapi/responses.py
hintapi/routing/__init__.py
hintapi/routing/commands.py
hintapi/routing/extensions/__init__.py
hintapi/routing/extensions/file.py
hintapi/routing/extensions/multimethod.py
hintapi/routing/routers.py
hintapi/routing/routes.py
hintapi/routing/tree.py
hintapi/status.py
hintapi/templates.py
hintapi/utils/__init__.py
hintapi/utils/contextvars.py
hintapi/utils/contextvars.pyi
hintapi/utils/importer.py
hintapi/utils/inspect.py
hintapi/utils/objects.py
hintapi/utils/pipe.py
hintapi/utils/register.py
hintapi/utils/state.py
hintapi/views.py
hintapi-0.22.14.dist-info/entry_points.txt
hintapi-0.22.14.dist-info/WHEEL
hintapi-0.22.14.dist-info/METADATA
hintapi-0.22.14.dist-info/licenses/LICENSE
hintapi-0.22.14.dist-info/RECORD
