Metadata-Version: 2.1
Name: hintapi
Version: 0.22.14
Summary: Web framework based on type hint.
License: Apache-2.0
Author-email: abersheeran <me@abersheeran.com>
Requires-Python: >=3.7
Classifier: License :: OSI Approved :: Apache Software License
Classifier: Programming Language :: Python :: 3
Classifier: Programming Language :: Python :: Implementation :: CPython
Requires-Dist: baize<1.0.0,>=0.15.0
Requires-Dist: pydantic<2.0,>=1.8
Requires-Dist: typing-extensions>=3.10.0
Provides-Extra: cli
Requires-Dist: click<9.0,>=8.0; extra == "cli"
Provides-Extra: serve
Requires-Dist: waitress>=2.0.0; extra == "serve"
Requires-Dist: hupper; extra == "serve"
Project-URL: documentation, https://hintapi.abersheeran.com/
Project-URL: homepage, https://github.com/abersheeran/hintapi
Project-URL: repository, https://github.com/abersheeran/hintapi
